README
setup.py
castro/__init__.py
castro.egg-info/PKG-INFO
castro.egg-info/SOURCES.txt
castro.egg-info/dependency_links.txt
castro.egg-info/entry_points.txt
castro.egg-info/not-zip-safe
castro.egg-info/requires.txt
castro.egg-info/top_level.txt
castro/lib/__init__.py
castro/lib/messageboard.py
castro/lib/pyvnc2swf/__init__.py
castro/lib/pyvnc2swf/d3des.py
castro/lib/pyvnc2swf/edit.py
castro/lib/pyvnc2swf/html_templates.py
castro/lib/pyvnc2swf/image.py
castro/lib/pyvnc2swf/movie.py
castro/lib/pyvnc2swf/mp3.py
castro/lib/pyvnc2swf/output.py
castro/lib/pyvnc2swf/play.py
castro/lib/pyvnc2swf/record_sound.py
castro/lib/pyvnc2swf/rfb.py
castro/lib/pyvnc2swf/swf.py
castro/lib/pyvnc2swf/vnc2swf.py