Metadata-Version: 1.0
Name: castro
Version: 1.0.6
Summary: Screencasting library
Home-page: http://github.com/hugs/castro
Author: Jason R. Huggins
Author-email: jason@jrandolph.com
License: GPL
Keywords: pyvnc2swf screencast video
Platform: UNKNOWN
Classifier: Development Status :: 4 - Beta
Classifier: Environment :: MacOS X
Classifier: Environment :: Win32 (MS Windows)
Classifier: Environment :: X11 Applications
Classifier: Intended Audience :: Developers
Classifier: License :: OSI Approved :: GNU General Public License (GPL)
Classifier: Operating System :: OS Independent
Classifier: Programming Language :: Python
Classifier: Topic :: Multimedia :: Graphics :: Capture :: Screen Capture
Classifier: Topic :: Software Development :: Libraries :: Python Modules
